retri_eval/__init__.py
retri_eval/evaluation/__init__.py
retri_eval/evaluation/indexed_task.py
retri_eval/evaluation/mteb_tasks.py
retri_eval/evaluation/retriever.py
retri_eval/indexes/__init__.py
retri_eval/indexes/indexing.py
retri_eval/indexes/qdrant_index.py
retri_eval/processing/__init__.py
retri_eval/processing/pipeline.py
retri_evals-0.0.1.dist-info/LICENSE
retri_evals-0.0.1.dist-info/METADATA
retri_evals-0.0.1.dist-info/WHEEL
retri_evals-0.0.1.dist-info/RECORD
