Metadata-Version: 2.1
Name: retri-evals
Version: 0.0.1
Summary: Open-source tool for building and evaluating retrieval pipelines.
Home-page: https://github.com/DeployQL/retri-evals
License: AGPL-3.0
Keywords: data-science,artificial-intelligence,developers-tools,mlops,rag,retrieval
Author: Matt Barta
Author-email: contact@deployql.com
Requires-Python: >=3.8,<3.12
Classifier: License :: OSI Approved :: GNU Affero General Public License v3
Classifier: Programming Language :: Python :: 3
Classifier: Programming Language :: Python :: 3.8
Classifier: Programming Language :: Python :: 3.9
Classifier: Programming Language :: Python :: 3.10
Classifier: Programming Language :: Python :: 3.11
Requires-Dist: beir (==2.0.0)
Requires-Dist: hruid (==0.0.3)
Requires-Dist: mteb (==1.1.1)
Requires-Dist: pydantic-settings (==2.1.0)
Requires-Dist: qdrant-client (==1.7.0)
Requires-Dist: tantivy (==0.21.0)
Requires-Dist: tokenizers (==0.14.1)
